{"tosaccept": true, "max_resolution": [1600, 900], "resolution": [1600, 900], "music": true, "sound": true, "music_vol": 0.391, "sound_vol": 0.055, "show_stats": true, "casual_score_goal": 0, "casual_ball_speed": 1, "casual_powerups": 4, "casual_ai_difficulty": 2, "comp_score_goal": 10, "comp_ball_speed": 1, "comp_serve_miss_penalty": 2, "comp_ball_speedup": true, "stats": {"total_bounces": 36277, "total_playtime": 21931.075033999994, "playtime_0": 20016.186427, "playtime_1": 762.2268260000001, "playtime_2": 459.95489999999995, "playtime_3": 693.673575, "total_powerups": 2858, "total_pixels_travelled": 14586653.244370056, "total_points_scored_p1": 616, "total_points_scored_p2": 231, "serves_missed": 213}}